ocbpy/__init__.py
ocbpy/_boundary.py
ocbpy/cycle_boundary.py
ocbpy/ocb_correction.py
ocbpy/ocb_scaling.py
ocbpy/ocb_time.py
ocbpy/vectors.py
ocbpy/boundaries/README.md
ocbpy/boundaries/__init__.py
ocbpy/boundaries/amp_north_radii.eab
ocbpy/boundaries/amp_north_radii.ocb
ocbpy/boundaries/amp_south_radii.eab
ocbpy/boundaries/amp_south_radii.ocb
ocbpy/boundaries/dmsp_ssj_files.py
ocbpy/boundaries/files.py
ocbpy/boundaries/image_north_circle.eab
ocbpy/boundaries/image_north_circle.ocb
ocbpy/boundaries/models.py
ocbpy/boundaries/si12_north_circle.eab
ocbpy/boundaries/si12_north_circle.ocb
ocbpy/boundaries/si13_north_circle.eab
ocbpy/boundaries/si13_north_circle.ocb
ocbpy/boundaries/wic_north_circle.eab
ocbpy/boundaries/wic_north_circle.ocb
ocbpy/boundaries/__pycache__/__init__.cpython-310.pyc
ocbpy/boundaries/__pycache__/__init__.cpython-39.pyc
ocbpy/boundaries/__pycache__/dmsp_ssj_files.cpython-310.pyc
ocbpy/boundaries/__pycache__/dmsp_ssj_files.cpython-39.pyc
ocbpy/boundaries/__pycache__/files.cpython-310.pyc
ocbpy/boundaries/__pycache__/files.cpython-39.pyc
ocbpy/boundaries/__pycache__/models.cpython-310.pyc
ocbpy/boundaries/__pycache__/models.cpython-39.pyc
ocbpy/instruments/__init__.py
ocbpy/instruments/general.py
ocbpy/instruments/pysat_instruments.py
ocbpy/instruments/supermag.py
ocbpy/instruments/vort.py
ocbpy/tests/__init__.py
ocbpy/tests/class_common.py
ocbpy/tests/test_boundary_dual.py
ocbpy/tests/test_boundary_eab.py
ocbpy/tests/test_boundary_ocb.py
ocbpy/tests/test_cycle_boundary.py
ocbpy/tests/test_dmsp_ssj_files.py
ocbpy/tests/test_files.py
ocbpy/tests/test_general.py
ocbpy/tests/test_models.py
ocbpy/tests/test_ocb_correction.py
ocbpy/tests/test_ocb_scaling.py
ocbpy/tests/test_ocb_time.py
ocbpy/tests/test_pysat.py
ocbpy/tests/test_supermag.py
ocbpy/tests/test_vectors.py
ocbpy/tests/test_vort.py
ocbpy/tests/test_data/dmsp-f16_ssj_precipitating-electrons-ions_20101231_v1.1.2.cdf
ocbpy-0.6.0.dist-info/licenses/AUTHORS.rst
ocbpy-0.6.0.dist-info/licenses/LICENSE
ocbpy-0.6.0.dist-info/METADATA
ocbpy-0.6.0.dist-info/WHEEL
ocbpy-0.6.0.dist-info/top_level.txt
ocbpy-0.6.0.dist-info/RECORD
