Metadata-Version: 2.4
Name: ocbpy
Version: 0.6.0
Summary: Convert between magnetic/geodetic and adaptive, polar boundary coordinates
Maintainer-email: "Angeline G. Burrell" <angeline.g.burrell.civ@us.navy.mil>
License: Copyright (c) 2017, Angeline G. Burrell (AGB) and Gareth Chisham (GC)
Project-URL: source, https://github.com/aburrell/ocbpy
Project-URL: documentation, https://ocbpy.readthedocs.io/en/latest/
Project-URL: tracker, https://github.com/aburrell/ocbpy/issues
Project-URL: download, https://github.com/aburrell/ocbpy/releases
Keywords: coordinates,field-line boundary,auroral oval,polar cap,pysat,ionosphere,atmosphere,thermosphere,magnetosphere,heliosphere,observations,models,space,satellites,analysis
Classifier: Development Status :: 5 - Production/Stable
Classifier: Intended Audience :: Science/Research
Classifier: Topic :: Scientific/Engineering :: Atmospheric Science
Classifier: Topic :: Scientific/Engineering :: Physics
Classifier: License :: OSI Approved :: BSD License
Classifier: Natural Language :: English
Classifier: Programming Language :: Python
Classifier: Programming Language :: Python :: 3
Classifier: Programming Language :: Python :: 3.10
Classifier: Programming Language :: Python :: 3.11
Classifier: Programming Language :: Python :: 3.12
Classifier: Programming Language :: Python :: 3.13
Classifier: Operating System :: Unix
Classifier: Operating System :: POSIX
Classifier: Operating System :: POSIX :: Linux
Classifier: Operating System :: MacOS :: MacOS X
Classifier: Operating System :: Microsoft :: Windows
Requires-Python: >=3.10
License-File: LICENSE
License-File: AUTHORS.rst
Requires-Dist: aacgmv2
Requires-Dist: numpy
Provides-Extra: pysat-instruments
Requires-Dist: pysat>=3.2.1; extra == "pysat-instruments"
Provides-Extra: dmsp-ssj
Requires-Dist: zenodo-get; extra == "dmsp-ssj"
Provides-Extra: doc
Requires-Dist: numpydoc; extra == "doc"
Requires-Dist: pyproject-parser; extra == "doc"
Requires-Dist: pysat>=3.2.1; extra == "doc"
Requires-Dist: sphinx>=1.3; extra == "doc"
Requires-Dist: sphinx-rtd-theme; extra == "doc"
Requires-Dist: zenodo-get; extra == "doc"
Provides-Extra: test
Requires-Dist: coverage[toml]; extra == "test"
Requires-Dist: flake8; extra == "test"
Requires-Dist: packaging; extra == "test"
Requires-Dist: requests; extra == "test"
Dynamic: license-file
